classymail/settings.py
classymail/__init__.py
classymail/rendering/django.py
classymail/rendering/__init__.py
classymail/storage/__init__.py
classymail/transports/base.py
classymail/transports/django.py
classymail/transports/__init__.py
python_classymail-0.0.4.dist-info/DESCRIPTION.rst
python_classymail-0.0.4.dist-info/METADATA
python_classymail-0.0.4.dist-info/metadata.json
python_classymail-0.0.4.dist-info/RECORD
python_classymail-0.0.4.dist-info/top_level.txt
python_classymail-0.0.4.dist-info/WHEEL
